{
    "contract": "",
    "summary": "",
    "description": "",
    "project": {
        "name": "",
        "website": "",
        "logo_64x64": ""
    },
    "versions": [
        {
            "version": "", // Optional
            "compiler": "",
            "plutus_version": "",
            "royalty": "",
            "repository": "",
            "audit": { // Optional
                  "provider": "",
                  "report": "",
                  "date": ""
                },
            "client": "", // Optional
            "backend": "" // Optional
        }
    ]
}